labelu_ml/__init__.py
labelu_ml/api.py
labelu_ml/examples/the_simplest_app/__init__.py
labelu_ml/examples/the_simplest_app/_wsgi.py
labelu_ml/examples/the_simplest_app/model.py
labelu_ml/examples/the_simplest_app/requirements.txt
labelu_ml/main.py
labelu_ml/model.py
labelu_ml-0.1.0.dist-info/entry_points.txt
labelu_ml-0.1.0.dist-info/WHEEL
labelu_ml-0.1.0.dist-info/METADATA
labelu_ml-0.1.0.dist-info/RECORD
