Metadata-Version: 2.1
Name: labelu-ml
Version: 0.1.0
Summary: 
Author: pengjinhu
Author-email: pengjinhu@pjlab.org.cn
Requires-Python: >=3.7,<4.0
Classifier: Programming Language :: Python :: 3
Classifier: Programming Language :: Python :: 3.7
Classifier: Programming Language :: Python :: 3.8
Classifier: Programming Language :: Python :: 3.9
Classifier: Programming Language :: Python :: 3.10
Classifier: Programming Language :: Python :: 3.11
Requires-Dist: appdirs (>=1.4.4,<2.0.0)
Requires-Dist: fastapi (>=0.88.0,<0.89.0)
Requires-Dist: loguru (>=0.6.0,<0.7.0)
Requires-Dist: typer[all] (>=0.7.0,<0.8.0)
Requires-Dist: uvicorn (>=0.20.0,<0.21.0)
